devnest/__init__.py
devnest/lib/__init__.py
devnest/lib/cli.py
devnest/lib/exceptions.py
devnest/lib/jenkins.py
devnest/lib/logger.py
devnest/lib/node.py
devnest/lib/release.py
devnest-0.0.5.dist-info/licenses/AUTHORS
devnest-0.0.5.dist-info/licenses/LICENSE
devnest-0.0.5.dist-info/METADATA
devnest-0.0.5.dist-info/WHEEL
devnest-0.0.5.dist-info/entry_points.txt
devnest-0.0.5.dist-info/pbr.json
devnest-0.0.5.dist-info/top_level.txt
devnest-0.0.5.dist-info/RECORD
