Metadata-Version: 2.4
Name: devnest
Version: 0.0.5
Summary: TBD
Home-page: https://github.com/rhos-infra/devnest
Author: Michal Pryc
Author-email: rhos-ci@redhat.com
Maintainer: Michal Pryc
Maintainer-email: rhos-ci@redhat.com
License: BSD
Keywords: jenkins
Classifier: Development Status :: 5 - Production/Stable
Classifier: Environment :: Other Environment
Classifier: Intended Audience :: Developers
Classifier: Intended Audience :: Information Technology
Classifier: License :: OSI Approved :: Apache Software License
Classifier: Operating System :: OS Independent
Classifier: Programming Language :: Python
Classifier: Programming Language :: Python :: 2.7
Classifier: Programming Language :: Python :: 3
Classifier: Programming Language :: Python :: 3.4
Classifier: Programming Language :: Python :: 3.5
Classifier: Programming Language :: Python :: 3.6
Classifier: Topic :: Software Development :: Libraries :: Python Modules
Classifier: Topic :: Internet :: WWW/HTTP
License-File: LICENSE
License-File: AUTHORS
Requires-Dist: colorlog>=2.6.1
Requires-Dist: jenkinsapi
Requires-Dist: terminaltables>=3.1.0
Requires-Dist: urllib3
Requires-Dist: requests
Requires-Dist: distro
Requires-Dist: selinux
Dynamic: author
Dynamic: author-email
Dynamic: classifier
Dynamic: description
Dynamic: home-page
Dynamic: keywords
Dynamic: license
Dynamic: license-file
Dynamic: maintainer
Dynamic: maintainer-email
Dynamic: requires-dist
Dynamic: summary
